ipm/__init__.py
ipm/__main__.py
ipm/__version__.py
ipm/common.py
ipm/manage.py
ipm/version_check.py
ipmgr-1.2.0.dist-info/LICENSE
ipmgr-1.2.0.dist-info/METADATA
ipmgr-1.2.0.dist-info/WHEEL
ipmgr-1.2.0.dist-info/entry_points.txt
ipmgr-1.2.0.dist-info/RECORD
