Metadata-Version: 2.3
Name: ipmgr
Version: 1.2.0
Summary: Package manager for Open Source ASIC IPs
License: Apache-2.0
Author: Efabless Corporation
Author-email: marwan.abbas@efabless.com
Requires-Python: >=3.8.0
Classifier: License :: OSI Approved :: Apache Software License
Classifier: Programming Language :: Python :: 3
Classifier: Programming Language :: Python :: 3.8
Classifier: Programming Language :: Python :: 3.9
Classifier: Programming Language :: Python :: 3.10
Classifier: Programming Language :: Python :: 3.11
Classifier: Programming Language :: Python :: 3.12
Classifier: Programming Language :: Python :: 3.13
Requires-Dist: beautifulsoup4 (>=4.12.0,<5)
Requires-Dist: click (>=8.0.0,<9)
Requires-Dist: click-default-group
Requires-Dist: httpx (>0.22.0,<0.26.0)
Requires-Dist: pyyaml (>=5,<7)
Requires-Dist: requests (>=2.31.0,<3)
Requires-Dist: rich (>=12,<14)
Project-URL: Homepage, https://efabless.com
Project-URL: Repository, https://github.com/efabless/ipm
